sm2/LICENSE.txt
sm2/__init__.py
sm2/_version.py
sm2/api.py
sm2/conftest.py
sm2/setup.cfg
sm2/base/__init__.py
sm2/base/_constraints.py
sm2/base/covtype.py
sm2/base/data.py
sm2/base/elastic_net.py
sm2/base/l1_cvxopt.py
sm2/base/l1_slsqp.py
sm2/base/l1_solvers_common.py
sm2/base/model.py
sm2/base/naming.py
sm2/base/optimizer.py
sm2/base/wrapper.py
sm2/base/tests/__init__.py
sm2/base/tests/test_data.py
sm2/base/tests/test_generic_methods.py
sm2/base/tests/test_optimize.py
sm2/base/tests/test_predict.py
sm2/base/tests/test_shrink_pickle.py
sm2/compat/__init__.py
sm2/compat/numpy.py
sm2/compat/python.py
sm2/compat/scipy.py
sm2/compat/tests/__init__.py
sm2/compat/tests/test_scipy_compat.py
sm2/datasets/README.txt
sm2/datasets/__init__.py
sm2/datasets/template_data.py
sm2/datasets/utils.py
sm2/datasets/anes96/__init__.py
sm2/datasets/anes96/anes96.csv
sm2/datasets/anes96/data.py
sm2/datasets/cancer/__init__.py
sm2/datasets/cancer/cancer.csv
sm2/datasets/cancer/data.py
sm2/datasets/ccard/__init__.py
sm2/datasets/ccard/ccard.csv
sm2/datasets/ccard/data.py
sm2/datasets/china_smoking/__init__.py
sm2/datasets/china_smoking/china_smoking.csv
sm2/datasets/china_smoking/data.py
sm2/datasets/co2/__init__.py
sm2/datasets/co2/co2.csv
sm2/datasets/co2/data.py
sm2/datasets/committee/__init__.py
sm2/datasets/committee/committee.csv
sm2/datasets/committee/data.py
sm2/datasets/copper/__init__.py
sm2/datasets/copper/copper.csv
sm2/datasets/copper/data.py
sm2/datasets/cpunish/__init__.py
sm2/datasets/cpunish/cpunish.csv
sm2/datasets/cpunish/data.py
sm2/datasets/elnino/__init__.py
sm2/datasets/elnino/data.py
sm2/datasets/elnino/elnino.csv
sm2/datasets/engel/__init__.py
sm2/datasets/engel/data.py
sm2/datasets/engel/engel.csv
sm2/datasets/fair/__init__.py
sm2/datasets/fair/data.py
sm2/datasets/fair/fair.csv
sm2/datasets/fair/fair_pt.csv
sm2/datasets/fertility/__init__.py
sm2/datasets/fertility/data.py
sm2-0.1.3.dist-info/LICENSE.txt
sm2-0.1.3.dist-info/METADATA
sm2-0.1.3.dist-info/RECORD
sm2-0.1.3.dist-info/WHEEL
sm2-0.1.3.dist-info/top_level.txt
