Metadata-Version: 2.1
Name: sm2
Version: 0.1.3
Summary: Bugfix Fork of statsmodels
Home-page: UNKNOWN
Author: Brock Mendel
Author-email: jbrockmendel@gmail.com
License: BSD License
Platform: any
Classifier: Development Status :: 4 - Beta
Classifier: Environment :: Console
Classifier: Programming Language :: Cython
Classifier: Programming Language :: Python :: 2.7
Classifier: Programming Language :: Python :: 3.5
Classifier: Programming Language :: Python :: 3.6
Classifier: Programming Language :: Python :: 3.7
Classifier: Operating System :: OS Independent
Classifier: Intended Audience :: End Users/Desktop
Classifier: Intended Audience :: Developers
Classifier: Intended Audience :: Science/Research
Classifier: Natural Language :: English
Classifier: License :: OSI Approved :: BSD License
Classifier: Topic :: Scientific/Engineering
Requires-Dist: numpy (>=1.13.0)
Requires-Dist: scipy (>=0.19.0)
Requires-Dist: pandas (>=0.22.0)
Requires-Dist: patsy (>=0.4.0)
Provides-Extra: docs
Requires-Dist: sphinx (>=1.3.5); extra == 'docs'
Requires-Dist: matplotlib; extra == 'docs'
Requires-Dist: numpydoc (>=0.6.0); extra == 'docs'
